cant_stop/__init__.py
cant_stop/py.typed
cant_stop-0.0.1.dist-info/LICENSE
cant_stop-0.0.1.dist-info/METADATA
cant_stop-0.0.1.dist-info/WHEEL
cant_stop-0.0.1.dist-info/RECORD
