Metadata-Version: 2.1
Name: cant-stop
Version: 0.0.1
Summary: A Python implementation of Sid Sackson's dice game Can't Stop
Home-page: https://recommend-games.github.io/cant-stop
License: MIT
Author: Markus Shepherd
Author-email: markus@recommend.games
Requires-Python: >=3.8.1,<4.0
Classifier: Development Status :: 4 - Beta
Classifier: Intended Audience :: Developers
Classifier: License :: OSI Approved :: MIT License
Classifier: Operating System :: OS Independent
Classifier: Programming Language :: Python
Classifier: Programming Language :: Python :: 3
Classifier: Programming Language :: Python :: 3.9
Classifier: Programming Language :: Python :: 3.10
Classifier: Programming Language :: Python :: 3.11
Classifier: Programming Language :: Python :: 3.12
Classifier: Programming Language :: Python :: 3.13
Classifier: Programming Language :: Python :: 3.8
Classifier: Topic :: Software Development :: Libraries :: Python Modules
Classifier: Typing :: Typed
Project-URL: Documentation, https://recommend-games.github.io/cant-stop
Project-URL: Repository, https://github.com/recommend-games/cant-stop
